{
  "Scaling Engineer": {
    "debate_weight": 0.85,
    "spawn_count": 8,
    "last_updated": "2026-04-08T15:27:20.785924+00:00"
  },
  "Security Auditor": {
    "debate_weight": 0.88,
    "spawn_count": 8,
    "last_updated": "2026-04-08T15:27:20.786324+00:00"
  },
  "Product Strategist": {
    "debate_weight": 0.85,
    "spawn_count": 8,
    "last_updated": "2026-04-08T15:27:20.786854+00:00"
  },
  "Code Quality Engineer": {
    "debate_weight": 0.88,
    "spawn_count": 8,
    "last_updated": "2026-04-08T15:27:20.787070+00:00"
  },
  "CTO Watchdog": {
    "debate_weight": 0.88,
    "spawn_count": 8,
    "last_updated": "2026-04-08T15:27:20.787341+00:00"
  },
  "Risk Manager": {
    "debate_weight": 0.88,
    "spawn_count": 8,
    "last_updated": "2026-04-08T15:27:20.787607+00:00"
  },
  "Readiness Manager": {
    "debate_weight": 0.85,
    "spawn_count": 8,
    "last_updated": "2026-04-08T15:27:20.787908+00:00"
  },
  "Ecosystem Auditor": {
    "debate_weight": 0.85,
    "spawn_count": 8,
    "last_updated": "2026-04-08T15:27:20.788156+00:00"
  }
}