{
  "perspective": "Cultural Intelligence",
  "provider": "nvidia",
  "model": "meta/llama-3.3-70b-instruct",
  "raw": "{\"perspective\": \"Cultural Intelligence\", \"vote\": \"yes\", \"amendment_if_yes_amended\": \"Prioritize fixes that impact user experience and adhere to Foundation Laws\", \"rationale\": \"Fixing errors that affect user experience and adhere to Foundation Laws will improve the overall quality of the platform and ensure compliance with constitutional requirements\", \"risk_if_other_side_wins\": \"Delayed fixes may lead to increased user frustration, decreased engagement, and potential legal issues\", \"constitutional_violations_detected\": \"None\", \"whistleblower_flag\": \"null\"}",
  "vote": "yes",
  "amendment_if_yes_amended": "Prioritize fixes that impact user experience and adhere to Foundation Laws",
  "rationale": "Fixing errors that affect user experience and adhere to Foundation Laws will improve the overall quality of the platform and ensure compliance with constitutional requirements",
  "risk_if_other_side_wins": "Delayed fixes may lead to increased user frustration, decreased engagement, and potential legal issues",
  "constitutional_violations_detected": "None",
  "whistleblower_flag": "null"
}